copilot/__init__.py
copilot/context.py
copilot/conversation.py
copilot/history.py
copilot/history_file.py
copilot/main.py
copilot/messages_builder.py
copilot/open_ai_adapter.py
copilot/parse_args.py
copilot/parse_os.py
copilot/question.py
copilot/sample_conversations.py
copilot/shell_adapter.py
copilot/strip.py
copilot/test_copilot.py
copilot/test_history.py
copilot/test_messages_builder.py
copilot/test_shell.py
terminal_copilot-1.5.3.dist-info/LICENSE
terminal_copilot-1.5.3.dist-info/METADATA
terminal_copilot-1.5.3.dist-info/WHEEL
terminal_copilot-1.5.3.dist-info/entry_points.txt
terminal_copilot-1.5.3.dist-info/top_level.txt
terminal_copilot-1.5.3.dist-info/RECORD
