Metadata-Version: 2.1
Name: terminal-copilot
Version: 1.5.3
Summary: A smart terminal assistant that helps you find the right command
Home-page: https://github.com/Methexis-Inc/terminal-copilot
Author: Methexis
Author-email: joelkronander@gmail.com
License: Apache License 2.0
Keywords: terminal copilot openai gpt3 gpt4 gpt3.5
Classifier: Programming Language :: Python :: 3
Classifier: License :: OSI Approved :: Apache Software License
Classifier: Operating System :: OS Independent
License-File: LICENSE
Requires-Dist: certifi >=2022.12.7
Requires-Dist: et-xmlfile >=1.1.0
Requires-Dist: idna >=3.4
Requires-Dist: numpy >=1.21.6
Requires-Dist: openai >=0.27.0
Requires-Dist: openpyxl >=3.0.10
Requires-Dist: pandas >=1.3.5
Requires-Dist: python-dateutil >=2.8.2
Requires-Dist: pyperclip >=1.8.2
Requires-Dist: pytz >=2022.6
Requires-Dist: requests >=2.28.1
Requires-Dist: six >=1.16.0
Requires-Dist: tqdm >=4.64.1
Requires-Dist: types-pytz >=2022.6.0.1
Requires-Dist: typing-extensions >=4.4.0
Requires-Dist: urllib3 >=1.26.13
Requires-Dist: simple-term-menu >=1.6.1 ; sys_platform == "linux" or sys_platform == "linux2" or sys_platform == "darwin"
Requires-Dist: inquirer ; sys_platform == "win32"
